CHANGES
LICENSE
MANIFEST.in
README.rst
setup.py
snaked/__init__.py
snaked.egg-info/PKG-INFO
snaked.egg-info/SOURCES.txt
snaked.egg-info/dependency_links.txt
snaked.egg-info/entry_points.txt
snaked.egg-info/namespace_packages.txt
snaked.egg-info/not-zip-safe
snaked.egg-info/requires.txt
snaked.egg-info/top_level.txt
snaked/core/__init__.py
snaked/core/app.py
snaked/core/config.py
snaked/core/console.py
snaked/core/context.py
snaked/core/contexts.template
snaked/core/editor.py
snaked/core/feedback.py
snaked/core/manager.py
snaked/core/plugins.py
snaked/core/prefs.py
snaked/core/problems.py
snaked/core/processors.py
snaked/core/run.py
snaked/core/shortcuts.py
snaked/core/tabbed.py
snaked/core/titler.py
snaked/core/editor_list/__init__.py
snaked/core/editor_list/gui.glade
snaked/core/editor_list/gui.py
snaked/core/gui/__init__.py
snaked/core/gui/editor_prefs.glade
snaked/core/gui/editor_prefs.py
snaked/core/gui/new_file.py
snaked/core/gui/plugin_prefs.glade
snaked/core/gui/plugin_prefs.py
snaked/core/gui/prefs.glade
snaked/core/gui/prefs.py
snaked/core/gui/select_session.glade
snaked/core/gui/shortcuts.glade
snaked/core/gui/shortcuts.py
snaked/core/lang-specs/python.lang
snaked/core/lang-specs/rst.lang
snaked/core/lang-specs/snippets.lang
snaked/core/quick_open/__init__.py
snaked/core/quick_open/gui.glade
snaked/core/quick_open/gui.py
snaked/core/quick_open/searcher.py
snaked/core/quick_open/settings.py
snaked/plugins/__init__.py
snaked/plugins/complete_words/__init__.py
snaked/plugins/complete_words/words.py
snaked/plugins/edit_and_select/__init__.py
snaked/plugins/edit_and_select/bracket_matcher.py
snaked/plugins/edit_and_select/smart_select.py
snaked/plugins/edit_and_select/util.py
snaked/plugins/external_tools/__init__.py
snaked/plugins/external_tools/external.tools.template
snaked/plugins/external_tools/parser.py
snaked/plugins/goto_dir/__init__.py
snaked/plugins/goto_line/__init__.py
snaked/plugins/hash_comment/__init__.py
snaked/plugins/python/__init__.py
snaked/plugins/python/complete.py
snaked/plugins/python/djangohints.py
snaked/plugins/python/dochints.py
snaked/plugins/python/outline.glade
snaked/plugins/python/outline.py
snaked/plugins/python/plugin.py
snaked/plugins/python/pygtk_stubs.py
